stlin/__init__.py
stlin/frontend/build/index.css
stlin/frontend/build/index.html
stlin/frontend/build/index.js
stlin-0.1.0.dist-info/licenses/LICENSE
stlin-0.1.0.dist-info/METADATA
stlin-0.1.0.dist-info/WHEEL
stlin-0.1.0.dist-info/top_level.txt
stlin-0.1.0.dist-info/RECORD
