Metadata-Version: 2.4
Name: stlin
Version: 0.1.0
Summary: A Streamlit component for rendering data lineage from Cognite Data Fusion
Author-email: Everton Colling <evertoncolling@gmail.com>
License-Expression: MIT
Project-URL: Homepage, https://github.com/evertoncolling/stlin
Project-URL: Repository, https://github.com/evertoncolling/stlin
Project-URL: Issues, https://github.com/evertoncolling/stlin/issues
Keywords: streamlit,lineage,cognite,visualization,component
Classifier: Development Status :: 3 - Alpha
Classifier: Intended Audience :: Developers
Classifier: Programming Language :: Python :: 3
Classifier: Programming Language :: Python :: 3.9
Classifier: Programming Language :: Python :: 3.10
Classifier: Programming Language :: Python :: 3.11
Classifier: Programming Language :: Python :: 3.12
Classifier: Topic :: Software Development :: Libraries :: Python Modules
Requires-Python: >=3.9
License-File: LICENSE
Requires-Dist: streamlit>=1.28.0
Dynamic: license-file
